<?xml version="1.0" encoding="UTF-8"?>
<con:soapui-project id="34931c0f-6bf0-4224-8518-724bb876b1d3" activeEnvironment="Default" name="numberconversion" resourceRoot="" soapui-version="5.7.0" abortOnError="false" runType="SEQUENTIAL" xmlns:con="http://eviware.com/soapui/config"><con:settings/><con:interface xsi:type="con:WsdlInterface" id="cb206c48-a11d-4bab-9124-81373ddc4f72" wsaVersion="NONE" name="NumberConversionSoapBinding" type="wsdl" bindingName="{http://www.dataaccess.com/webservicesserver/}NumberConversionSoapBinding" soapVersion="1_1" anonymous="optional" definition="https://www.dataaccess.com/webservicesserver/numberconversion.wso?WSDL" xmlns:xsi="http://www.w3.org/2001/XMLSchema-instance"><con:settings><con:setting id="CreateWsdlDocumentationAction@report-directory">G:\sprint3.apitesting\soapui</con:setting></con:settings><con:definitionCache/><con:endpoints><con:endpoint>https://www.dataaccess.com/webservicesserver/numberconversion.wso</con:endpoint></con:endpoints><con:operation id="5042cb4d-0dae-4582-a164-0ed043566e99" isOneWay="false" action="" name="NumberToDollars" bindingOperationName="NumberToDollars" type="Request-Response" inputName="" receivesAttachments="false" sendsAttachments="false" anonymous="optional"><con:settings/><con:call id="024e9b08-1927-45dc-bf92-9dff66078ae8" name="Request 1"><con:settings><con:setting id="com.eviware.soapui.impl.wsdl.WsdlRequest@request-headers">&lt;xml-fragment/></con:setting></con:settings><con:encoding>UTF-8</con:encoding><con:endpoint>https://www.dataaccess.com/webservicesserver/numberconversion.wso</con:endpoint><con:request><![CDATA[<soapenv:Envelope xmlns:soapenv="http://schemas.xmlsoap.org/soap/envelope/" xmlns:web="http://www.dataaccess.com/webservicesserver/">\r
   <soapenv:Header/>\r
   <soapenv:Body>\r
      <web:NumberToDollars>\r
         <web:dNum>10</web:dNum>\r
      </web:NumberToDollars>\r
   </soapenv:Body>\r
</soapenv:Envelope>]]></con:request><con:credentials><con:authType>No Authorization</con:authType></con:credentials><con:jmsConfig JMSDeliveryMode="PERSISTENT"/><con:jmsPropertyConfig/><con:wsaConfig mustUnderstand="NONE" version="200508" action="http://www.dataaccess.com/webservicesserver/NumberConversionSoapType/NumberToDollarsRequest"/><con:wsrmConfig version="1.2"/></con:call></con:operation><con:operation id="7d035c8e-93d8-4b9a-b7f1-fd0a1df15695" isOneWay="false" action="" name="NumberToWords" bindingOperationName="NumberToWords" type="Request-Response" inputName="" receivesAttachments="false" sendsAttachments="false" anonymous="optional"><con:settings/><con:call id="380410f8-2b69-4c0b-aff6-38f26ee3a483" name="Request 1"><con:settings><con:setting id="com.eviware.soapui.impl.wsdl.WsdlRequest@request-headers">&lt;xml-fragment/></con:setting></con:settings><con:encoding>UTF-8</con:encoding><con:endpoint>https://www.dataaccess.com/webservicesserver/numberconversion.wso</con:endpoint><con:request><![CDATA[<soapenv:Envelope xmlns:soapenv="http://schemas.xmlsoap.org/soap/envelope/" xmlns:web="http://www.dataaccess.com/webservicesserver/">\r
   <soapenv:Header/>\r
   <soapenv:Body>\r
      <web:NumberToWords>\r
         <web:ubiNum>10</web:ubiNum>\r
      </web:NumberToWords>\r
   </soapenv:Body>\r
</soapenv:Envelope>]]></con:request><con:credentials><con:authType>No Authorization</con:authType></con:credentials><con:jmsConfig JMSDeliveryMode="PERSISTENT"/><con:jmsPropertyConfig/><con:wsaConfig mustUnderstand="NONE" version="200508" action="http://www.dataaccess.com/webservicesserver/NumberConversionSoapType/NumberToWordsRequest"/><con:wsrmConfig version="1.2"/></con:call></con:operation></con:interface><con:testSuite id="6ab9b674-65ba-4c64-b3e6-22be782c0a71" name="TestSuite"><con:settings/><con:runType>SEQUENTIAL</con:runType><con:testCase id="29cb7b87-81c3-4cb9-a423-a1ad0bf56639" failOnError="true" failTestCaseOnErrors="true" keepSession="false" maxResults="0" name="NumberToDollars TestCase" searchProperties="true"><con:settings/><con:testStep type="request" id="f08767e1-3141-472a-8961-fb2123373cb7" name="NumberToDollars"><con:settings/><con:config xsi:type="con:RequestStep" xmlns:xsi="http://www.w3.org/2001/XMLSchema-instance"><con:interface>NumberConversionSoapBinding</con:interface><con:operation>NumberToDollars</con:operation><con:request name="NumberToDollars" id="3336e012-2b80-413d-a43e-f43300824eba"><con:settings><con:setting id="com.eviware.soapui.impl.wsdl.WsdlRequest@request-headers">&lt;xml-fragment/></con:setting></con:settings><con:encoding>UTF-8</con:encoding><con:endpoint>https://www.dataaccess.com/webservicesserver/numberconversion.wso</con:endpoint><con:request><![CDATA[<soapenv:Envelope xmlns:soapenv="http://schemas.xmlsoap.org/soap/envelope/" xmlns:web="http://www.dataaccess.com/webservicesserver/">\r
   <soapenv:Header/>\r
   <soapenv:Body>\r
      <web:NumberToDollars>\r
         <web:dNum>12</web:dNum>\r
      </web:NumberToDollars>\r
   </soapenv:Body>\r
</soapenv:Envelope>]]></con:request><con:assertion type="Response SLA Assertion" id="25fc3b4b-c7a4-401c-a75a-7410ebc1e0a2" name="Response SLA"><con:configuration><SLA>3000</SLA></con:configuration></con:assertion><con:assertion type="Valid HTTP Status Codes" id="2dfe2d6b-79eb-4d57-8d51-d96cb37a9445" name="Valid HTTP Status Codes"><con:configuration><codes>200</codes></con:configuration></con:assertion><con:assertion type="GroovyScriptAssertion" id="6bc9c836-41e4-451f-b1d9-fa9d2765ef4e" name="Script Assertion"><con:configuration><scriptText>//validate response nodes
def groovyUtils = new com.eviware.soapui.support.GroovyUtils( context )
def responseHolder = groovyUtils.getXmlHolder( messageExchange.responseContent )
def result = responseHolder.getNodeValue("//m:NumberToDollarsResult")
assert result == "twelve dollars"</scriptText></con:configuration></con:assertion><con:credentials><con:authType>No Authorization</con:authType></con:credentials><con:jmsConfig JMSDeliveryMode="PERSISTENT"/><con:jmsPropertyConfig/><con:wsaConfig action="http://www.dataaccess.com/webservicesserver/NumberConversionSoapType/NumberToDollarsRequest" mustUnderstand="NONE" version="200508"/><con:wsrmConfig version="1.2"/></con:request></con:config></con:testStep><con:properties/></con:testCase><con:testCase id="06fb962e-979f-4fa0-a8ea-5956cc6c0fe6" failOnError="true" failTestCaseOnErrors="true" keepSession="false" maxResults="0" name="NumberToWords TestCase" searchProperties="true"><con:settings/><con:testStep type="request" id="2603a2d9-4116-4f4f-9141-c40d00d4e379" name="NumberToWords"><con:settings/><con:config xsi:type="con:RequestStep" xmlns:xsi="http://www.w3.org/2001/XMLSchema-instance"><con:interface>NumberConversionSoapBinding</con:interface><con:operation>NumberToWords</con:operation><con:request name="NumberToWords" id="f008af73-ba36-4e6a-bfdd-5365c9cbe618"><con:settings><con:setting id="com.eviware.soapui.impl.wsdl.WsdlRequest@request-headers">&lt;xml-fragment/></con:setting></con:settings><con:encoding>UTF-8</con:encoding><con:endpoint>https://www.dataaccess.com/webservicesserver/numberconversion.wso</con:endpoint><con:request><![CDATA[<soapenv:Envelope xmlns:soapenv="http://schemas.xmlsoap.org/soap/envelope/" xmlns:web="http://www.dataaccess.com/webservicesserver/">\r
   <soapenv:Header/>\r
   <soapenv:Body>\r
      <web:NumberToWords>\r
         <web:ubiNum>10</web:ubiNum>\r
      </web:NumberToWords>\r
   </soapenv:Body>\r
</soapenv:Envelope>]]></con:request><con:assertion type="Response SLA Assertion" id="629680e8-88bc-474a-858e-094e0514b868" name="Response SLA"><con:configuration><SLA>3000</SLA></con:configuration></con:assertion><con:assertion type="Valid HTTP Status Codes" id="fe5e9d78-fa08-41c0-a673-9043ea0526aa" name="Valid HTTP Status Codes"><con:configuration><codes>200</codes></con:configuration></con:assertion><con:assertion type="GroovyScriptAssertion" id="ba6ea28b-98df-4158-8c89-eebe004cd061" name="Script Assertion"><con:configuration><scriptText>//validate response nodes
def groovyUtils = new com.eviware.soapui.support.GroovyUtils( context )
def responseHolder = groovyUtils.getXmlHolder( messageExchange.responseContent )
def result = responseHolder.getNodeValue("//m:NumberToWordsResult")
assert result == "ten"</scriptText></con:configuration></con:assertion><con:credentials><con:authType>No Authorization</con:authType></con:credentials><con:jmsConfig JMSDeliveryMode="PERSISTENT"/><con:jmsPropertyConfig/><con:wsaConfig action="http://www.dataaccess.com/webservicesserver/NumberConversionSoapType/NumberToWordsRequest" mustUnderstand="NONE" version="200508"/><con:wsrmConfig version="1.2"/></con:request></con:config></con:testStep><con:properties/></con:testCase><con:properties/></con:testSuite><con:properties/><con:wssContainer/><con:oAuth2ProfileContainer/><con:oAuth1ProfileContainer/><con:sensitiveInformation/></con:soapui-project>